py.typed
orq_python_client/__init__.py
orq_python_client/_hooks/__init__.py
orq_python_client/_hooks/registration.py
orq_python_client/_hooks/sdkhooks.py
orq_python_client/_hooks/types.py
orq_python_client/_version.py
orq_python_client/basesdk.py
orq_python_client/contacts.py
orq_python_client/deployments_sdk.py
orq_python_client/feedback.py
orq_python_client/files.py
orq_python_client/httpclient.py
orq_python_client/models/__init__.py
orq_python_client/models/delete_v2_resources_datasets_dataset_id_op.py
orq_python_client/models/delete_v2_resources_datasets_dataset_id_rows_bulkop.py
orq_python_client/models/delete_v2_resources_datasets_dataset_id_rows_row_id_op.py
orq_python_client/models/deployments.py
orq_python_client/models/get_v2_resources_datasets_dataset_id_op.py
orq_python_client/models/get_v2_resources_datasets_dataset_id_rows_row_id_op.py
orq_python_client/models/get_v2_resources_datasets_dataset_id_rowsop.py
orq_python_client/models/get_v2_resources_datasetsop.py
orq_python_client/models/patch_v2_resources_datasets_dataset_id_op.py
orq_python_client/models/patch_v2_resources_datasets_dataset_id_rows_row_id_op.py
orq_python_client/models/post_contactsop.py
orq_python_client/models/post_feedbackop.py
orq_python_client/models/post_v2_deployments_get_configop.py
orq_python_client/models/post_v2_deployments_id_metricsop.py
orq_python_client/models/post_v2_deployments_invokeop.py
orq_python_client/models/post_v2_files_bulkop.py
orq_python_client/models/post_v2_filesop.py
orq_python_client/models/post_v2_resources_datasets_dataset_id_rows_bulkop.py
orq_python_client/models/post_v2_resources_datasets_dataset_id_rowsop.py
orq_python_client/models/post_v2_resources_datasetsop.py
orq_python_client/models/post_v2_router_chat_completionsop.py
orq_python_client/models/post_v2_router_completionsop.py
orq_python_client/models/post_v2_router_embeddingsop.py
orq_python_client/models/post_v2_router_images_generationsop.py
orq_python_client-0.0.1.dist-info/METADATA
orq_python_client-0.0.1.dist-info/WHEEL
orq_python_client-0.0.1.dist-info/RECORD
